passhole/__init__.py
passhole/blank.kdbx
passhole/passhole.py
passhole/version.py
passhole/wordlist.txt
passhole-1.9.4.dist-info/LICENSE
passhole-1.9.4.dist-info/METADATA
passhole-1.9.4.dist-info/WHEEL
passhole-1.9.4.dist-info/entry_points.txt
passhole-1.9.4.dist-info/top_level.txt
passhole-1.9.4.dist-info/RECORD
