Metadata-Version: 2.1
Name: passhole
Version: 1.9.4
Summary: CLI KeePass client with dmenu support
Home-page: https://github.com/evidlo/passhole
Author: Evan Widloski
Author-email: evan@evanw.org
License: GPLv3
Keywords: keepass cli dmenu password store passwords manager rofi pykeepass libkeepass
Platform: UNKNOWN
Classifier: Programming Language :: Python :: 3
Requires-Dist: pynput
Requires-Dist: pykeepass-cache
Requires-Dist: colorama
Requires-Dist: future
